molextract/__init__.py
molextract/debug.py
molextract/parser.py
molextract/rule.py
molextract/rules/__init__.py
molextract/rules/abstract.py
molextract/rules/gaussian/__init__.py
molextract/rules/gaussian/general.py
molextract/rules/gaussian/log.py
molextract/rules/gaussian/tddft.py
molextract/rules/molcas/__init__.py
molextract/rules/molcas/general.py
molextract/rules/molcas/log.py
molextract/rules/molcas/mcpdft.py
molextract/rules/molcas/rasscf.py
molextract/rules/molcas/rassi.py
molextract-1.0.0.dist-info/LICENSE
molextract-1.0.0.dist-info/METADATA
molextract-1.0.0.dist-info/WHEEL
molextract-1.0.0.dist-info/top_level.txt
molextract-1.0.0.dist-info/RECORD
