Metadata-Version: 2.1
Name: molextract
Version: 1.0.0
Summary: Parse Molcas/OpenMolcas log files in a modular way
Author-email: Nithin Chintala <chintala.v@northeastern.edu>
License: GNU GENERAL PUBLIC LICENSE
Project-URL: Homepage, https://github.com/sdonglab/molextract
Keywords: chemistry,computational-chemistry,log-files,parsing,parser,molcas,open-molcas
Classifier: Intended Audience :: Science/Research
Classifier: License :: OSI Approved :: GNU General Public License v2 (GPLv2)
Classifier: Topic :: Scientific/Engineering :: Chemistry
Requires-Python: >=3.7
License-File: LICENSE
